{"sections":{"d990486d-47f7-4a20-9baf-69a18b23ca50":{"type":"image-banner","blocks":{"2c4fe820-5002-43ab-8f98-c8e89242bac3":{"type":"heading","settings":{"heading":"404","heading_size":"h0","heading_h1":true}},"731725ed-8319-4326-9a9e-82337aa3e951":{"type":"subheading","settings":{"text":"Oops! We seem to have dropped the ball!"}},"12526dec-55ae-491c-ab38-faf0eab65d9c":{"type":"text","settings":{"text":"<p>Sorry, the page you requested does not exist.<\/p>","enlarge_text":false}},"c7eb209e-c55a-44f9-8e47-aef50bc9fdb7":{"type":"button","settings":{"button_1_label":"Back to Home","button_1_link":"\/","button_1_style":"btn btn--primary","button_2_label":"","button_2_link":"","button_2_style":"btn btn--primary"}}},"block_order":["2c4fe820-5002-43ab-8f98-c8e89242bac3","731725ed-8319-4326-9a9e-82337aa3e951","12526dec-55ae-491c-ab38-faf0eab65d9c","c7eb209e-c55a-44f9-8e47-aef50bc9fdb7"],"settings":{"image_desktop":"shopify:\/\/shop_images\/ASICS_AW23_CPS_Indoor_Highlight-Photography_Higher_2.jpg","url":"","height_mode":"fixed","fixed_height_desktop":500,"fixed_height_mobile":350,"overlay_position":"justify-center items-center","overlay_text_align":"text-center","mob_center_text":false,"mobile_stacked":false,"color_scheme":"white","full_width":true,"transparent_content_color":"#ffffff","tint_color":"#000000","tint_opacity":30,"prevent_animation":false}},"main":{"type":"main-404","disabled":true,"settings":{}},"e91f5d47-904a-4d6e-9046-eb8b8f91d4b1":{"type":"rich-text","blocks":{"template--21617239425310__e91f5d47-904a-4d6e-9046-eb8b8f91d4b1-text-1":{"type":"text","settings":{"text":"<p>We're here to serve you but it looks like the page you were looking for doesn't exist. That's our fault!<br\/><br\/>Feel free to call us at <a href=\"tel:1-888-962-7077\" title=\"tel:1-888-962-7077\"><strong>1-888-962-7077<\/strong><\/a> or email us if there is anything we can do to assist with your gear needs!<\/p>","enlarge_text":false}}},"block_order":["template--21617239425310__e91f5d47-904a-4d6e-9046-eb8b8f91d4b1-text-1"],"settings":{"text_position":"justify-center","text_align":"text-center","mob_center_text":true,"color_scheme":"1","full_width":true,"prevent_animation":false}},"c0b8be70-96ac-4dc7-80b6-c4b2f58ed81b":{"type":"featured-collection","disabled":true,"settings":{"title":"Top collections","heading_align":"text-start","show_view_all":true,"collection":"","layout":"carousel","card_size_mobile":"small","card_size":"small","products_to_show":8,"show_promo_info":false,"image_ratio":"fill","promo_title":"A headline to grab attention","content":"<p>Use this card with an image to highlight your collections or introduce a promotion.<\/p>","link_url":"","button_label":"Button","color_scheme":"2","button_style":"btn btn--primary"}}},"order":["d990486d-47f7-4a20-9baf-69a18b23ca50","main","e91f5d47-904a-4d6e-9046-eb8b8f91d4b1","c0b8be70-96ac-4dc7-80b6-c4b2f58ed81b"]}